stable_baselines3/__init__.py
stable_baselines3/py.typed
stable_baselines3/version.txt
stable_baselines3/a2c/__init__.py
stable_baselines3/a2c/a2c.py
stable_baselines3/a2c/policies.py
stable_baselines3/common/__init__.py
stable_baselines3/common/atari_wrappers.py
stable_baselines3/common/base_class.py
stable_baselines3/common/buffers.py
stable_baselines3/common/callbacks.py
stable_baselines3/common/distributions.py
stable_baselines3/common/env_checker.py
stable_baselines3/common/env_util.py
stable_baselines3/common/evaluation.py
stable_baselines3/common/logger.py
stable_baselines3/common/monitor.py
stable_baselines3/common/noise.py
stable_baselines3/common/off_policy_algorithm.py
stable_baselines3/common/on_policy_algorithm.py
stable_baselines3/common/policies.py
stable_baselines3/common/preprocessing.py
stable_baselines3/common/results_plotter.py
stable_baselines3/common/running_mean_std.py
stable_baselines3/common/save_util.py
stable_baselines3/common/torch_layers.py
stable_baselines3/common/type_aliases.py
stable_baselines3/common/utils.py
stable_baselines3/common/envs/__init__.py
stable_baselines3/common/envs/bit_flipping_env.py
stable_baselines3/common/envs/identity_env.py
stable_baselines3/common/envs/multi_input_envs.py
stable_baselines3/common/sb2_compat/__init__.py
stable_baselines3/common/sb2_compat/rmsprop_tf_like.py
stable_baselines3/common/vec_env/__init__.py
stable_baselines3/common/vec_env/base_vec_env.py
stable_baselines3/common/vec_env/dummy_vec_env.py
stable_baselines3/common/vec_env/patch_gym.py
stable_baselines3/common/vec_env/stacked_observations.py
stable_baselines3/common/vec_env/subproc_vec_env.py
stable_baselines3/common/vec_env/util.py
stable_baselines3/common/vec_env/vec_check_nan.py
stable_baselines3/common/vec_env/vec_extract_dict_obs.py
stable_baselines3/common/vec_env/vec_frame_stack.py
stable_baselines3/common/vec_env/vec_monitor.py
stable_baselines3/common/vec_env/vec_normalize.py
stable_baselines3/common/vec_env/vec_transpose.py
stable_baselines3-2.4.0.dist-info/LICENSE
stable_baselines3-2.4.0.dist-info/METADATA
stable_baselines3-2.4.0.dist-info/NOTICE
stable_baselines3-2.4.0.dist-info/WHEEL
stable_baselines3-2.4.0.dist-info/top_level.txt
stable_baselines3-2.4.0.dist-info/RECORD
