Metadata-Version: 2.1
Name: stable_baselines3
Version: 2.4.0
Summary: Pytorch version of Stable Baselines, implementations of reinforcement learning algorithms.
Home-page: https://github.com/DLR-RM/stable-baselines3
Author: Antonin Raffin
Author-email: antonin.raffin@dlr.de
License: MIT
Project-URL: Code, https://github.com/DLR-RM/stable-baselines3
Project-URL: Documentation, https://stable-baselines3.readthedocs.io/
Project-URL: Changelog, https://stable-baselines3.readthedocs.io/en/master/misc/changelog.html
Project-URL: SB3-Contrib, https://github.com/Stable-Baselines-Team/stable-baselines3-contrib
Project-URL: RL-Zoo, https://github.com/DLR-RM/rl-baselines3-zoo
Project-URL: SBX, https://github.com/araffin/sbx
Keywords: reinforcement-learning-algorithms reinforcement-learning machine-learning gymnasium gym openai stable baselines toolbox python data-science
Classifier: Programming Language :: Python :: 3
Classifier: Programming Language :: Python :: 3.8
Classifier: Programming Language :: Python :: 3.9
Classifier: Programming Language :: Python :: 3.10
Classifier: Programming Language :: Python :: 3.11
Requires-Python: >=3.8
License-File: LICENSE
License-File: NOTICE
Requires-Dist: gymnasium<1.1.0,>=0.29.1
Requires-Dist: numpy<2.0,>=1.20
Requires-Dist: torch>=1.13
Requires-Dist: cloudpickle
Requires-Dist: pandas
Requires-Dist: matplotlib
Provides-Extra: tests
Requires-Dist: pytest; extra == "tests"
Requires-Dist: pytest-cov; extra == "tests"
Requires-Dist: pytest-env; extra == "tests"
Requires-Dist: pytest-xdist; extra == "tests"
Requires-Dist: mypy; extra == "tests"
Requires-Dist: ruff>=0.3.1; extra == "tests"
Requires-Dist: black<25,>=24.2.0; extra == "tests"
Provides-Extra: docs
Requires-Dist: sphinx<9,>=5; extra == "docs"
Requires-Dist: sphinx-autobuild; extra == "docs"
Requires-Dist: sphinx-rtd-theme>=1.3.0; extra == "docs"
Requires-Dist: sphinxcontrib.spelling; extra == "docs"
Requires-Dist: sphinx_copybutton; extra == "docs"
Provides-Extra: extra
Requires-Dist: opencv-python; extra == "extra"
Requires-Dist: pygame; extra == "extra"
Requires-Dist: tensorboard>=2.9.1; extra == "extra"
Requires-Dist: psutil; extra == "extra"
Requires-Dist: tqdm; extra == "extra"
Requires-Dist: rich; extra == "extra"
Requires-Dist: ale-py>=0.9.0; extra == "extra"
Requires-Dist: pillow; extra == "extra"
